ihist/__init__.py
ihist/_ihist.cpython-310-x86_64-linux-gnu.so
ihist-0.1.3.dist-info/METADATA
ihist-0.1.3.dist-info/WHEEL
ihist-0.1.3.dist-info/RECORD
